Guias/Guia_09/clock.v
// ---------------------------
// Nome: Victor Souza Lima
// Matricula: 835287
// ---------------------------

module clock ( output clk );
reg clk;
initial
begin
clk = 1'b0;
end
always
begin
#12 clk = ~clk;
end
endmodule //

Guias/Guia_09/Guia_0902.v
// ---------------------------
// Nome: Victor Souza Lima
// Matricula: 835287
// ---------------------------
`include "clock.v"

module pulse1 ( signal, clock );
input clock;
output signal;
reg signal;
always @ ( posedge clock )
begin
signal = 1'b1;
#1 signal = 1'b0;
#1 signal = 1'b1;
#1 signal = 1'b0;
end
endmodule // pulse

module pulse2 ( signal, clock );
input clock;
output signal;
reg signal;
always @ ( posedge clock )
begin
signal = 1'b1;
#5 signal = 1'b0;
#5 signal = 1'b1;
#5 signal = 1'b0;
end
endmodule // pulse

module pulse3 ( signal, clock );
input clock;
output signal;
reg signal;
always @ ( negedge clock )
begin
signal = 1'b1;
#15 signal = 1'b0;
#15 signal = 1'b1;
#15 signal = 1'b0;
#15 signal = 1'b1;
end
endmodule // pulse

module pulse4 ( signal, clock );
input clock;
output signal;
reg signal;
always @ ( negedge clock )
begin
signal = 1'b1;
#20 signal = 1'b0;
#20 signal = 1'b1;
end
endmodule // pulse

module Guia_0902;
wire clock;
clock clk ( clock );
wire p1,p2,p3,p4;
pulse1 pls1 ( p1, clock );
pulse2 pls2 ( p2, clock );
pulse3 pls3 ( p3, clock );
pulse4 pls4 ( p4, clock );
initial begin
$dumpfile ( " Guia_0902.vcd" );
$dumpvars ( 1, clock, p1, p2, p3, p4 );
#480 $finish;
end
endmodule // Guia_0902

Guias/Guia_09/Guia_0902.vcd
$date
	Sun Apr 14 11:49:48 2024
$end
$version
	Icarus Verilog
$end
$timescale
	1s
$end
$scope module Guia_0902 $end
$var wire 1 ! clock $end
$upscope $end
$scope module Guia_0902 $end
$var wire 1 " p1 $end
$upscope $end
$scope module Guia_0902 $end
$var wire 1 # p2 $end
$upscope $end
$scope module Guia_0902 $end
$var wire 1 $ p3 $end
$upscope $end
$scope module Guia_0902 $end
$var wire 1 % p4 $end
$upscope $end
$enddefinitions $end
$comment Show the parameter values. $end
$dumpall
$end
#0
$dumpvars
x%
x$
x#
x"
0!
$end
#12
1"
1#
1!
#13
0"
#14
1"
#15
0"
#17
0#
#22
1#
#24
1$
1%
0!
#27
0#
#36
1"
1#
1!
#37
0"
#38
1"
#39
0"
0$
#41
0#
#44
0%
#46
1#
#48
0!
#51
0#
#54
1$
#60
1"
1#
1!
#61
0"
#62
1"
#63
0"
#64
1%
#65
0#
#69
0$
#70
1#
#72
0!
#75
0#
#84
1"
1#
1!
1$
#85
0"
#86
1"
#87
0"
#89
0#
#92
0%
#94
1#
#96
0!
#99
0#
#108
1"
1#
1!
#109
0"
#110
1"
#111
0"
0$
#112
1%
#113
0#
#118
1#
#120
0!
#123
0#
#126
1$
#132
1"
1#
1!
#133
0"
#134
1"
#135
0"
#137
0#
#140
0%
#141
0$
#142
1#
#144
0!
#147
0#
#156
1"
1#
1!
1$
#157
0"
#158
1"
#159
0"
#160
1%
#161
0#
#166
1#
#168
0!
#171
0#
#180
1"
1#
1!
#181
0"
#182
1"
#183
0"
0$
#185
0#
#188
0%
#190
1#
#192
0!
#195
0#
#198
1$
#204
1"
1#
1!
#205
0"
#206
1"
#207
0"
#208
1%
#209
0#
#213
0$
#214
1#
#216
0!
#219
0#
#228
1"
1#
1!
1$
#229
0"
#230
1"
#231
0"
#233
0#
#236
0%
#238
1#
#240
0!
#243
0#
#252
1"
1#
1!
#253
0"
#254
1"
#255
0"
0$
#256
1%
#257
0#
#262
1#
#264
0!
#267
0#
#270
1$
#276
1"
1#
1!
#277
0"
#278
1"
#279
0"
#281
0#
#284
0%
#285
0$
#286
1#
#288
0!
#291
0#
#300
1"
1#
1!
1$
#301
0"
#302
1"
#303
0"
#304
1%
#305
0#
#310
1#
#312
0!
#315
0#
#324
1"
1#
1!
#325
0"
#326
1"
#327
0"
0$
#329
0#
#332
0%
#334
1#
#336
0!
#339
0#
#342
1$
#348
1"
1#
1!
#349
0"
#350
1"
#351
0"
#352
1%
#353
0#
#357
0$
#358
1#
#360
0!
#363
0#
#372
1"
1#
1!
1$
#373
0"
#374
1"
#375
0"
#377
0#
#380
0%
#382
1#
#384
0!
#387
0#
#396
1"
1#
1!
#397
0"
#398
1"
#399
0"
0$
#400
1%
#401
0#
#406
1#
#408
0!
#411
0#
#414
1$
#420
1"
1#
1!
#421
0"
#422
1"
#423
0"
#425
0#
#428
0%
#429
0$
#430
1#
#432
0!
#435
0#
#444
1"
1#
1!
1$
#445
0"
#446
1"
#447
0"
#448
1%
#449
0#
#454
1#
#456
0!
#459
0#
#468
1"
1#
1!
#469
0"
#470
1"
#471
0"
0$
#473
0#
#476
0%
#478
1#
